Metadata-Version: 1.0
Name: zw
Version: 0.0.1
Summary: 吃枣药丸
Home-page: https://zhuanlan.zhihu.com/p/26159930
Author: Vvgoder
Author-email: 1060825598@qq.com
License: UNKNOWN
Platform: UNKNOWN
